pysshexec.py
python_ssh_exec-0.1.3.dist-info/LICENSE
python_ssh_exec-0.1.3.dist-info/METADATA
python_ssh_exec-0.1.3.dist-info/WHEEL
python_ssh_exec-0.1.3.dist-info/entry_points.txt
python_ssh_exec-0.1.3.dist-info/top_level.txt
python_ssh_exec-0.1.3.dist-info/RECORD
