Metadata-Version: 2.1
Name: python-ssh-exec
Version: 0.1.3
Summary: A library to execute local python scripts on remote servers.
Home-page: https://github.com/AdamGold/python-ssh-exec
Author: AdamGold
Author-email: adamgold7@gmail.com
License: UNKNOWN
Platform: UNKNOWN
Requires-Dist: Click (==7.0)
Requires-Dist: paramiko (==2.4.2)
Requires-Dist: cryptography (==2.4.2)
